{
  "keyword": "人人都是中国智驾合伙人",
  "platform": "dy",
  "items": [
    {
      "title": "人人都是中国智驾合伙人最新训练视频出炉",
      "url": "https://dy.com/video/833118",
      "comments": [
        {
          "user": "用户8747",
          "text": "这个视频拍得真不错，很有现场感",
          "likes": 23,
          "time": "2025-12-08 15:45:41"
        },
        {
          "user": "用户8802",
          "text": "这个视频拍得真不错，很有现场感",
          "likes": 278,
          "time": "2025-12-08 15:45:41"
        },
        {
          "user": "用户4074",
          "text": "支持人人都是中国智驾合伙人，为他们点赞",
          "likes": 3,
          "time": "2025-12-08 15:45:41"
        }
      ],
      "platform": "dy",
      "create_time": "2025-12-08 15:45:41",
      "likes": 3940,
      "views": 59262,
      "author": "创作者9418"
    },
    {
      "title": "直击人人都是中国智驾合伙人现场，精彩瞬间",
      "url": "https://dy.com/video/959868",
      "comments": [
        {
          "user": "用户6446",
          "text": "这个人人都是中国智驾合伙人视频太震撼了！",
          "likes": 316,
          "time": "2025-12-08 15:45:41"
        },
        {
          "user": "用户1560",
          "text": "这个视频拍得真不错，很有现场感",
          "likes": 153,
          "time": "2025-12-08 15:45:41"
        },
        {
          "user": "用户3454",
          "text": "这个人人都是中国智驾合伙人视频太震撼了！",
          "likes": 351,
          "time": "2025-12-08 15:45:41"
        },
        {
          "user": "用户9068",
          "text": "这个人人都是中国智驾合伙人视频太震撼了！",
          "likes": 456,
          "time": "2025-12-08 15:45:41"
        },
        {
          "user": "用户4759",
          "text": "这个视频拍得真不错，很有现场感",
          "likes": 456,
          "time": "2025-12-08 15:45:41"
        },
        {
          "user": "用户3054",
          "text": "支持人人都是中国智驾合伙人，为他们点赞",
          "likes": 72,
          "time": "2025-12-08 15:45:41"
        },
        {
          "user": "用户2543",
          "text": "没想到人人都是中国智驾合伙人还有这样的一面",
          "likes": 74,
          "time": "2025-12-08 15:45:41"
        },
        {
          "user": "用户6671",
          "text": "支持人人都是中国智驾合伙人，为他们点赞",
          "likes": 9,
          "time": "2025-12-08 15:45:41"
        },
        {
          "user": "用户7676",
          "text": "这个视频拍得真不错，很有现场感",
          "likes": 346,
          "time": "2025-12-08 15:45:41"
        },
        {
          "user": "用户4020",
          "text": "这个视频拍得真不错，很有现场感",
          "likes": 159,
          "time": "2025-12-08 15:45:41"
        },
        {
          "user": "用户7034",
          "text": "支持人人都是中国智驾合伙人，为他们点赞",
          "likes": 452,
          "time": "2025-12-08 15:45:41"
        },
        {
          "user": "用户4795",
          "text": "这个人人都是中国智驾合伙人视频太震撼了！",
          "likes": 214,
          "time": "2025-12-08 15:45:41"
        },
        {
          "user": "用户2052",
          "text": "没想到人人都是中国智驾合伙人还有这样的一面",
          "likes": 225,
          "time": "2025-12-08 15:45:41"
        },
        {
          "user": "用户3804",
          "text": "这个人人都是中国智驾合伙人视频太震撼了！",
          "likes": 281,
          "time": "2025-12-08 15:45:41"
        },
        {
          "user": "用户1827",
          "text": "没想到人人都是中国智驾合伙人还有这样的一面",
          "likes": 378,
          "time": "2025-12-08 15:45:41"
        }
      ],
      "platform": "dy",
      "create_time": "2025-12-08 15:45:41",
      "likes": 4607,
      "views": 49695,
      "author": "创作者9856"
    },
    {
      "title": "震撼！人人都是中国智驾合伙人最新动态曝光",
      "url": "https://dy.com/video/834900",
      "comments": [
        {
          "user": "用户9320",
          "text": "人人都是中国智驾合伙人训练看起来很专业",
          "likes": 310,
          "time": "2025-12-08 15:45:41"
        },
        {
          "user": "用户8864",
          "text": "没想到人人都是中国智驾合伙人还有这样的一面",
          "likes": 252,
          "time": "2025-12-08 15:45:41"
        },
        {
          "user": "用户3969",
          "text": "这个视频拍得真不错，很有现场感",
          "likes": 4,
          "time": "2025-12-08 15:45:41"
        }
      ],
      "platform": "dy",
      "create_time": "2025-12-08 15:45:41",
      "likes": 9278,
      "views": 79809,
      "author": "创作者4847"
    },
    {
      "title": "人人都是中国智驾合伙人最新训练视频出炉",
      "url": "https://dy.com/video/848037",
      "comments": [
        {
          "user": "用户6034",
          "text": "支持人人都是中国智驾合伙人，为他们点赞",
          "likes": 61,
          "time": "2025-12-08 15:45:41"
        },
        {
          "user": "用户3795",
          "text": "这个视频拍得真不错，很有现场感",
          "likes": 34,
          "time": "2025-12-08 15:45:41"
        },
        {
          "user": "用户5116",
          "text": "这个视频拍得真不错，很有现场感",
          "likes": 153,
          "time": "2025-12-08 15:45:41"
        },
        {
          "user": "用户8601",
          "text": "这个人人都是中国智驾合伙人视频太震撼了！",
          "likes": 211,
          "time": "2025-12-08 15:45:41"
        },
        {
          "user": "用户9120",
          "text": "人人都是中国智驾合伙人训练看起来很专业",
          "likes": 389,
          "time": "2025-12-08 15:45:41"
        },
        {
          "user": "用户9354",
          "text": "这个人人都是中国智驾合伙人视频太震撼了！",
          "likes": 134,
          "time": "2025-12-08 15:45:41"
        },
        {
          "user": "用户4733",
          "text": "没想到人人都是中国智驾合伙人还有这样的一面",
          "likes": 72,
          "time": "2025-12-08 15:45:41"
        },
        {
          "user": "用户7790",
          "text": "人人都是中国智驾合伙人训练看起来很专业",
          "likes": 229,
          "time": "2025-12-08 15:45:41"
        },
        {
          "user": "用户5951",
          "text": "没想到人人都是中国智驾合伙人还有这样的一面",
          "likes": 196,
          "time": "2025-12-08 15:45:41"
        },
        {
          "user": "用户6789",
          "text": "人人都是中国智驾合伙人训练看起来很专业",
          "likes": 132,
          "time": "2025-12-08 15:45:41"
        },
        {
          "user": "用户2670",
          "text": "人人都是中国智驾合伙人训练看起来很专业",
          "likes": 101,
          "time": "2025-12-08 15:45:41"
        },
        {
          "user": "用户9511",
          "text": "支持人人都是中国智驾合伙人，为他们点赞",
          "likes": 322,
          "time": "2025-12-08 15:45:41"
        },
        {
          "user": "用户3647",
          "text": "支持人人都是中国智驾合伙人，为他们点赞",
          "likes": 305,
          "time": "2025-12-08 15:45:41"
        },
        {
          "user": "用户9115",
          "text": "这个视频拍得真不错，很有现场感",
          "likes": 425,
          "time": "2025-12-08 15:45:41"
        },
        {
          "user": "用户8243",
          "text": "这个视频拍得真不错，很有现场感",
          "likes": 240,
          "time": "2025-12-08 15:45:41"
        }
      ],
      "platform": "dy",
      "create_time": "2025-12-08 15:45:41",
      "likes": 7834,
      "views": 63300,
      "author": "创作者1774"
    },
    {
      "title": "深度解析：人人都是中国智驾合伙人背后的故事",
      "url": "https://dy.com/video/544011",
      "comments": [
        {
          "user": "用户7475",
          "text": "这个视频拍得真不错，很有现场感",
          "likes": 480,
          "time": "2025-12-08 15:45:41"
        },
        {
          "user": "用户6198",
          "text": "支持人人都是中国智驾合伙人，为他们点赞",
          "likes": 304,
          "time": "2025-12-08 15:45:41"
        },
        {
          "user": "用户7297",
          "text": "人人都是中国智驾合伙人训练看起来很专业",
          "likes": 291,
          "time": "2025-12-08 15:45:41"
        },
        {
          "user": "用户6957",
          "text": "这个人人都是中国智驾合伙人视频太震撼了！",
          "likes": 41,
          "time": "2025-12-08 15:45:41"
        },
        {
          "user": "用户3536",
          "text": "这个视频拍得真不错，很有现场感",
          "likes": 275,
          "time": "2025-12-08 15:45:41"
        },
        {
          "user": "用户2206",
          "text": "这个视频拍得真不错，很有现场感",
          "likes": 313,
          "time": "2025-12-08 15:45:41"
        },
        {
          "user": "用户1642",
          "text": "这个人人都是中国智驾合伙人视频太震撼了！",
          "likes": 261,
          "time": "2025-12-08 15:45:41"
        },
        {
          "user": "用户4235",
          "text": "支持人人都是中国智驾合伙人，为他们点赞",
          "likes": 281,
          "time": "2025-12-08 15:45:41"
        },
        {
          "user": "用户3579",
          "text": "这个视频拍得真不错，很有现场感",
          "likes": 162,
          "time": "2025-12-08 15:45:41"
        },
        {
          "user": "用户2920",
          "text": "这个人人都是中国智驾合伙人视频太震撼了！",
          "likes": 44,
          "time": "2025-12-08 15:45:41"
        },
        {
          "user": "用户8045",
          "text": "这个视频拍得真不错，很有现场感",
          "likes": 17,
          "time": "2025-12-08 15:45:41"
        },
        {
          "user": "用户1858",
          "text": "这个视频拍得真不错，很有现场感",
          "likes": 243,
          "time": "2025-12-08 15:45:41"
        },
        {
          "user": "用户2317",
          "text": "没想到人人都是中国智驾合伙人还有这样的一面",
          "likes": 162,
          "time": "2025-12-08 15:45:41"
        },
        {
          "user": "用户6202",
          "text": "人人都是中国智驾合伙人训练看起来很专业",
          "likes": 284,
          "time": "2025-12-08 15:45:41"
        },
        {
          "user": "用户1967",
          "text": "支持人人都是中国智驾合伙人，为他们点赞",
          "likes": 72,
          "time": "2025-12-08 15:45:41"
        }
      ],
      "platform": "dy",
      "create_time": "2025-12-08 15:45:41",
      "likes": 5758,
      "views": 86916,
      "author": "创作者4351"
    }
  ],
  "total_items": 5,
  "total_comments": 51,
  "timestamp": "2025-12-08 15:45:41"
}