{
  "keyword": "再发冲突",
  "platform": "dy",
  "items": [
    {
      "title": "深度解析：再发冲突背后的故事",
      "url": "https://dy.com/video/428365",
      "comments": [
        {
          "user": "用户8993",
          "text": "没想到再发冲突还有这样的一面",
          "likes": 360,
          "time": "2025-12-08 15:15:42"
        },
        {
          "user": "用户7869",
          "text": "支持再发冲突，为他们点赞",
          "likes": 17,
          "time": "2025-12-08 15:15:42"
        },
        {
          "user": "用户4829",
          "text": "支持再发冲突，为他们点赞",
          "likes": 280,
          "time": "2025-12-08 15:15:42"
        },
        {
          "user": "用户5386",
          "text": "再发冲突训练看起来很专业",
          "likes": 478,
          "time": "2025-12-08 15:15:42"
        },
        {
          "user": "用户4474",
          "text": "没想到再发冲突还有这样的一面",
          "likes": 234,
          "time": "2025-12-08 15:15:42"
        },
        {
          "user": "用户4200",
          "text": "这个再发冲突视频太震撼了！",
          "likes": 369,
          "time": "2025-12-08 15:15:42"
        },
        {
          "user": "用户7954",
          "text": "没想到再发冲突还有这样的一面",
          "likes": 68,
          "time": "2025-12-08 15:15:42"
        },
        {
          "user": "用户2812",
          "text": "没想到再发冲突还有这样的一面",
          "likes": 265,
          "time": "2025-12-08 15:15:42"
        },
        {
          "user": "用户6488",
          "text": "这个视频拍得真不错，很有现场感",
          "likes": 32,
          "time": "2025-12-08 15:15:42"
        },
        {
          "user": "用户7200",
          "text": "支持再发冲突，为他们点赞",
          "likes": 266,
          "time": "2025-12-08 15:15:42"
        }
      ],
      "platform": "dy",
      "create_time": "2025-12-08 15:15:42",
      "likes": 5616,
      "views": 86967,
      "author": "创作者3952"
    },
    {
      "title": "直击再发冲突现场，精彩瞬间",
      "url": "https://dy.com/video/696966",
      "comments": [
        {
          "user": "用户9754",
          "text": "没想到再发冲突还有这样的一面",
          "likes": 163,
          "time": "2025-12-08 15:15:42"
        },
        {
          "user": "用户3152",
          "text": "这个再发冲突视频太震撼了！",
          "likes": 436,
          "time": "2025-12-08 15:15:42"
        },
        {
          "user": "用户1482",
          "text": "这个视频拍得真不错，很有现场感",
          "likes": 168,
          "time": "2025-12-08 15:15:42"
        },
        {
          "user": "用户4015",
          "text": "支持再发冲突，为他们点赞",
          "likes": 129,
          "time": "2025-12-08 15:15:42"
        },
        {
          "user": "用户1715",
          "text": "没想到再发冲突还有这样的一面",
          "likes": 407,
          "time": "2025-12-08 15:15:42"
        },
        {
          "user": "用户5782",
          "text": "没想到再发冲突还有这样的一面",
          "likes": 15,
          "time": "2025-12-08 15:15:42"
        },
        {
          "user": "用户4320",
          "text": "支持再发冲突，为他们点赞",
          "likes": 283,
          "time": "2025-12-08 15:15:42"
        },
        {
          "user": "用户9382",
          "text": "这个再发冲突视频太震撼了！",
          "likes": 96,
          "time": "2025-12-08 15:15:42"
        },
        {
          "user": "用户6730",
          "text": "支持再发冲突，为他们点赞",
          "likes": 401,
          "time": "2025-12-08 15:15:42"
        },
        {
          "user": "用户6562",
          "text": "支持再发冲突，为他们点赞",
          "likes": 435,
          "time": "2025-12-08 15:15:42"
        },
        {
          "user": "用户7363",
          "text": "这个视频拍得真不错，很有现场感",
          "likes": 409,
          "time": "2025-12-08 15:15:42"
        },
        {
          "user": "用户2112",
          "text": "这个视频拍得真不错，很有现场感",
          "likes": 294,
          "time": "2025-12-08 15:15:42"
        }
      ],
      "platform": "dy",
      "create_time": "2025-12-08 15:15:42",
      "likes": 9180,
      "views": 31818,
      "author": "创作者6969"
    },
    {
      "title": "深度解析：再发冲突背后的故事",
      "url": "https://dy.com/video/794942",
      "comments": [
        {
          "user": "用户5085",
          "text": "再发冲突训练看起来很专业",
          "likes": 156,
          "time": "2025-12-08 15:15:42"
        },
        {
          "user": "用户8416",
          "text": "再发冲突训练看起来很专业",
          "likes": 442,
          "time": "2025-12-08 15:15:42"
        },
        {
          "user": "用户6682",
          "text": "支持再发冲突，为他们点赞",
          "likes": 208,
          "time": "2025-12-08 15:15:42"
        },
        {
          "user": "用户4774",
          "text": "这个视频拍得真不错，很有现场感",
          "likes": 93,
          "time": "2025-12-08 15:15:42"
        },
        {
          "user": "用户7344",
          "text": "支持再发冲突，为他们点赞",
          "likes": 378,
          "time": "2025-12-08 15:15:42"
        }
      ],
      "platform": "dy",
      "create_time": "2025-12-08 15:15:42",
      "likes": 5998,
      "views": 82112,
      "author": "创作者5664"
    },
    {
      "title": "再发冲突最新训练视频出炉",
      "url": "https://dy.com/video/804472",
      "comments": [
        {
          "user": "用户2365",
          "text": "这个再发冲突视频太震撼了！",
          "likes": 76,
          "time": "2025-12-08 15:15:42"
        },
        {
          "user": "用户3356",
          "text": "支持再发冲突，为他们点赞",
          "likes": 133,
          "time": "2025-12-08 15:15:42"
        },
        {
          "user": "用户2513",
          "text": "没想到再发冲突还有这样的一面",
          "likes": 39,
          "time": "2025-12-08 15:15:42"
        },
        {
          "user": "用户6657",
          "text": "这个视频拍得真不错，很有现场感",
          "likes": 93,
          "time": "2025-12-08 15:15:42"
        },
        {
          "user": "用户6758",
          "text": "这个视频拍得真不错，很有现场感",
          "likes": 490,
          "time": "2025-12-08 15:15:42"
        },
        {
          "user": "用户5720",
          "text": "这个视频拍得真不错，很有现场感",
          "likes": 17,
          "time": "2025-12-08 15:15:42"
        },
        {
          "user": "用户8469",
          "text": "再发冲突训练看起来很专业",
          "likes": 100,
          "time": "2025-12-08 15:15:42"
        },
        {
          "user": "用户5333",
          "text": "没想到再发冲突还有这样的一面",
          "likes": 291,
          "time": "2025-12-08 15:15:42"
        },
        {
          "user": "用户6499",
          "text": "这个再发冲突视频太震撼了！",
          "likes": 386,
          "time": "2025-12-08 15:15:42"
        }
      ],
      "platform": "dy",
      "create_time": "2025-12-08 15:15:42",
      "likes": 8392,
      "views": 13594,
      "author": "创作者5055"
    },
    {
      "title": "再发冲突最新训练视频出炉",
      "url": "https://dy.com/video/663697",
      "comments": [
        {
          "user": "用户7604",
          "text": "再发冲突训练看起来很专业",
          "likes": 328,
          "time": "2025-12-08 15:15:42"
        },
        {
          "user": "用户4541",
          "text": "支持再发冲突，为他们点赞",
          "likes": 114,
          "time": "2025-12-08 15:15:42"
        },
        {
          "user": "用户3750",
          "text": "再发冲突训练看起来很专业",
          "likes": 186,
          "time": "2025-12-08 15:15:42"
        },
        {
          "user": "用户5510",
          "text": "支持再发冲突，为他们点赞",
          "likes": 240,
          "time": "2025-12-08 15:15:42"
        },
        {
          "user": "用户9462",
          "text": "这个视频拍得真不错，很有现场感",
          "likes": 308,
          "time": "2025-12-08 15:15:42"
        },
        {
          "user": "用户8025",
          "text": "没想到再发冲突还有这样的一面",
          "likes": 228,
          "time": "2025-12-08 15:15:42"
        },
        {
          "user": "用户7868",
          "text": "这个再发冲突视频太震撼了！",
          "likes": 387,
          "time": "2025-12-08 15:15:42"
        },
        {
          "user": "用户3454",
          "text": "这个再发冲突视频太震撼了！",
          "likes": 208,
          "time": "2025-12-08 15:15:42"
        },
        {
          "user": "用户2876",
          "text": "这个视频拍得真不错，很有现场感",
          "likes": 329,
          "time": "2025-12-08 15:15:42"
        },
        {
          "user": "用户8208",
          "text": "支持再发冲突，为他们点赞",
          "likes": 325,
          "time": "2025-12-08 15:15:42"
        },
        {
          "user": "用户2017",
          "text": "再发冲突训练看起来很专业",
          "likes": 318,
          "time": "2025-12-08 15:15:42"
        }
      ],
      "platform": "dy",
      "create_time": "2025-12-08 15:15:42",
      "likes": 2339,
      "views": 44068,
      "author": "创作者1290"
    }
  ],
  "total_items": 5,
  "total_comments": 47,
  "timestamp": "2025-12-08 15:15:42"
}