{
  "keyword": "难道不是想要爆米花吗",
  "platform": "dy",
  "items": [
    {
      "title": "直击难道不是想要爆米花吗现场，精彩瞬间",
      "url": "https://dy.com/video/124635",
      "comments": [
        {
          "user": "用户6407",
          "text": "没想到难道不是想要爆米花吗还有这样的一面",
          "likes": 368,
          "time": "2025-12-08 15:26:07"
        },
        {
          "user": "用户7261",
          "text": "这个难道不是想要爆米花吗视频太震撼了！",
          "likes": 105,
          "time": "2025-12-08 15:26:07"
        },
        {
          "user": "用户5546",
          "text": "难道不是想要爆米花吗训练看起来很专业",
          "likes": 138,
          "time": "2025-12-08 15:26:07"
        },
        {
          "user": "用户3399",
          "text": "支持难道不是想要爆米花吗，为他们点赞",
          "likes": 368,
          "time": "2025-12-08 15:26:07"
        },
        {
          "user": "用户4438",
          "text": "这个视频拍得真不错，很有现场感",
          "likes": 162,
          "time": "2025-12-08 15:26:07"
        },
        {
          "user": "用户5074",
          "text": "支持难道不是想要爆米花吗，为他们点赞",
          "likes": 190,
          "time": "2025-12-08 15:26:07"
        },
        {
          "user": "用户7607",
          "text": "难道不是想要爆米花吗训练看起来很专业",
          "likes": 203,
          "time": "2025-12-08 15:26:07"
        },
        {
          "user": "用户3206",
          "text": "支持难道不是想要爆米花吗，为他们点赞",
          "likes": 77,
          "time": "2025-12-08 15:26:07"
        },
        {
          "user": "用户5169",
          "text": "支持难道不是想要爆米花吗，为他们点赞",
          "likes": 472,
          "time": "2025-12-08 15:26:07"
        }
      ],
      "platform": "dy",
      "create_time": "2025-12-08 15:26:07",
      "likes": 3537,
      "views": 57510,
      "author": "创作者2513"
    },
    {
      "title": "震撼！难道不是想要爆米花吗最新动态曝光",
      "url": "https://dy.com/video/125084",
      "comments": [
        {
          "user": "用户5445",
          "text": "这个难道不是想要爆米花吗视频太震撼了！",
          "likes": 290,
          "time": "2025-12-08 15:26:07"
        },
        {
          "user": "用户4788",
          "text": "这个视频拍得真不错，很有现场感",
          "likes": 223,
          "time": "2025-12-08 15:26:07"
        },
        {
          "user": "用户3581",
          "text": "支持难道不是想要爆米花吗，为他们点赞",
          "likes": 430,
          "time": "2025-12-08 15:26:07"
        },
        {
          "user": "用户7658",
          "text": "难道不是想要爆米花吗训练看起来很专业",
          "likes": 69,
          "time": "2025-12-08 15:26:07"
        },
        {
          "user": "用户8150",
          "text": "没想到难道不是想要爆米花吗还有这样的一面",
          "likes": 94,
          "time": "2025-12-08 15:26:07"
        },
        {
          "user": "用户3737",
          "text": "这个视频拍得真不错，很有现场感",
          "likes": 158,
          "time": "2025-12-08 15:26:07"
        },
        {
          "user": "用户1903",
          "text": "没想到难道不是想要爆米花吗还有这样的一面",
          "likes": 193,
          "time": "2025-12-08 15:26:07"
        },
        {
          "user": "用户6194",
          "text": "没想到难道不是想要爆米花吗还有这样的一面",
          "likes": 451,
          "time": "2025-12-08 15:26:07"
        },
        {
          "user": "用户4196",
          "text": "这个视频拍得真不错，很有现场感",
          "likes": 419,
          "time": "2025-12-08 15:26:07"
        },
        {
          "user": "用户4565",
          "text": "难道不是想要爆米花吗训练看起来很专业",
          "likes": 39,
          "time": "2025-12-08 15:26:07"
        },
        {
          "user": "用户3936",
          "text": "支持难道不是想要爆米花吗，为他们点赞",
          "likes": 442,
          "time": "2025-12-08 15:26:07"
        },
        {
          "user": "用户4437",
          "text": "这个视频拍得真不错，很有现场感",
          "likes": 465,
          "time": "2025-12-08 15:26:07"
        },
        {
          "user": "用户4083",
          "text": "难道不是想要爆米花吗训练看起来很专业",
          "likes": 413,
          "time": "2025-12-08 15:26:07"
        }
      ],
      "platform": "dy",
      "create_time": "2025-12-08 15:26:07",
      "likes": 5294,
      "views": 52707,
      "author": "创作者6191"
    },
    {
      "title": "震撼！难道不是想要爆米花吗最新动态曝光",
      "url": "https://dy.com/video/831346",
      "comments": [
        {
          "user": "用户6298",
          "text": "支持难道不是想要爆米花吗，为他们点赞",
          "likes": 362,
          "time": "2025-12-08 15:26:07"
        },
        {
          "user": "用户6803",
          "text": "支持难道不是想要爆米花吗，为他们点赞",
          "likes": 4,
          "time": "2025-12-08 15:26:07"
        },
        {
          "user": "用户2213",
          "text": "难道不是想要爆米花吗训练看起来很专业",
          "likes": 328,
          "time": "2025-12-08 15:26:07"
        },
        {
          "user": "用户5850",
          "text": "支持难道不是想要爆米花吗，为他们点赞",
          "likes": 328,
          "time": "2025-12-08 15:26:07"
        },
        {
          "user": "用户9830",
          "text": "支持难道不是想要爆米花吗，为他们点赞",
          "likes": 141,
          "time": "2025-12-08 15:26:07"
        },
        {
          "user": "用户2648",
          "text": "支持难道不是想要爆米花吗，为他们点赞",
          "likes": 294,
          "time": "2025-12-08 15:26:07"
        },
        {
          "user": "用户6497",
          "text": "支持难道不是想要爆米花吗，为他们点赞",
          "likes": 181,
          "time": "2025-12-08 15:26:07"
        },
        {
          "user": "用户5421",
          "text": "没想到难道不是想要爆米花吗还有这样的一面",
          "likes": 214,
          "time": "2025-12-08 15:26:07"
        },
        {
          "user": "用户8406",
          "text": "支持难道不是想要爆米花吗，为他们点赞",
          "likes": 273,
          "time": "2025-12-08 15:26:07"
        },
        {
          "user": "用户4740",
          "text": "难道不是想要爆米花吗训练看起来很专业",
          "likes": 272,
          "time": "2025-12-08 15:26:07"
        }
      ],
      "platform": "dy",
      "create_time": "2025-12-08 15:26:07",
      "likes": 9894,
      "views": 92561,
      "author": "创作者5184"
    },
    {
      "title": "难道不是想要爆米花吗现场实拍：难道不是想要爆米花吗训练情况",
      "url": "https://dy.com/video/240533",
      "comments": [
        {
          "user": "用户6834",
          "text": "这个难道不是想要爆米花吗视频太震撼了！",
          "likes": 219,
          "time": "2025-12-08 15:26:07"
        },
        {
          "user": "用户7056",
          "text": "支持难道不是想要爆米花吗，为他们点赞",
          "likes": 207,
          "time": "2025-12-08 15:26:07"
        },
        {
          "user": "用户2325",
          "text": "支持难道不是想要爆米花吗，为他们点赞",
          "likes": 390,
          "time": "2025-12-08 15:26:07"
        },
        {
          "user": "用户3629",
          "text": "这个视频拍得真不错，很有现场感",
          "likes": 14,
          "time": "2025-12-08 15:26:07"
        },
        {
          "user": "用户1632",
          "text": "这个难道不是想要爆米花吗视频太震撼了！",
          "likes": 320,
          "time": "2025-12-08 15:26:07"
        },
        {
          "user": "用户7646",
          "text": "难道不是想要爆米花吗训练看起来很专业",
          "likes": 268,
          "time": "2025-12-08 15:26:07"
        },
        {
          "user": "用户9242",
          "text": "这个视频拍得真不错，很有现场感",
          "likes": 411,
          "time": "2025-12-08 15:26:07"
        },
        {
          "user": "用户8339",
          "text": "支持难道不是想要爆米花吗，为他们点赞",
          "likes": 277,
          "time": "2025-12-08 15:26:07"
        }
      ],
      "platform": "dy",
      "create_time": "2025-12-08 15:26:07",
      "likes": 5389,
      "views": 19019,
      "author": "创作者7813"
    },
    {
      "title": "直击难道不是想要爆米花吗现场，精彩瞬间",
      "url": "https://dy.com/video/848857",
      "comments": [
        {
          "user": "用户9069",
          "text": "这个视频拍得真不错，很有现场感",
          "likes": 477,
          "time": "2025-12-08 15:26:07"
        },
        {
          "user": "用户5137",
          "text": "这个难道不是想要爆米花吗视频太震撼了！",
          "likes": 273,
          "time": "2025-12-08 15:26:07"
        },
        {
          "user": "用户7956",
          "text": "这个难道不是想要爆米花吗视频太震撼了！",
          "likes": 348,
          "time": "2025-12-08 15:26:07"
        },
        {
          "user": "用户9240",
          "text": "这个视频拍得真不错，很有现场感",
          "likes": 110,
          "time": "2025-12-08 15:26:07"
        },
        {
          "user": "用户4308",
          "text": "难道不是想要爆米花吗训练看起来很专业",
          "likes": 412,
          "time": "2025-12-08 15:26:07"
        },
        {
          "user": "用户9540",
          "text": "难道不是想要爆米花吗训练看起来很专业",
          "likes": 247,
          "time": "2025-12-08 15:26:07"
        },
        {
          "user": "用户4702",
          "text": "支持难道不是想要爆米花吗，为他们点赞",
          "likes": 348,
          "time": "2025-12-08 15:26:07"
        },
        {
          "user": "用户5741",
          "text": "支持难道不是想要爆米花吗，为他们点赞",
          "likes": 356,
          "time": "2025-12-08 15:26:07"
        }
      ],
      "platform": "dy",
      "create_time": "2025-12-08 15:26:07",
      "likes": 7067,
      "views": 68689,
      "author": "创作者3560"
    }
  ],
  "total_items": 5,
  "total_comments": 48,
  "timestamp": "2025-12-08 15:26:07"
}